AppiumLibrary/__init__.py
AppiumLibrary/appium_path.py
AppiumLibrary/version.py
AppiumLibrary/keywords/__init__.py
AppiumLibrary/keywords/_applicationmanagement.py
AppiumLibrary/keywords/_element.py
AppiumLibrary/keywords/_logging.py
AppiumLibrary/keywords/_runonfailure.py
AppiumLibrary/keywords/_screenrecord.py
AppiumLibrary/keywords/_screenshot.py
AppiumLibrary/keywords/_waiting.py
AppiumLibrary/keywords/keywordgroup.py
AppiumLibrary/locators/__init__.py
AppiumLibrary/locators/elementfinder.py
AppiumLibrary/utils/__init__.py
AppiumLibrary/utils/applicationcache.py
robotframework_appiumlibrary_windows-0.1.0.dist-info/licenses/LICENSE
robotframework_appiumlibrary_windows-0.1.0.dist-info/METADATA
robotframework_appiumlibrary_windows-0.1.0.dist-info/WHEEL
robotframework_appiumlibrary_windows-0.1.0.dist-info/top_level.txt
robotframework_appiumlibrary_windows-0.1.0.dist-info/RECORD
