Metadata-Version: 2.4
Name: robotframework-appiumlibrary-windows
Version: 0.1.0
Summary: Robot Framework AppiumLibrary update
Author-email: Huy Nguyen <nguyenvanhuy0612@gmail.com>
License: MIT
Project-URL: Homepage, https://github.com/nguyenvanhuy0612/robotframework-appium-windows
Requires-Python: >=3.10
License-File: LICENSE
Requires-Dist: robotframework>=7.2.2
Requires-Dist: Appium-Python-Client==5.1.1
Requires-Dist: decorator==5.2.1
Requires-Dist: six==1.17.0
Dynamic: license-file
